[
  {
    "value": "{withsecure.infection.name} infection found on {host.hostname}: {file.path}",
    "conditions": [
      {
        "field": "host.hostname"
      },
      {
        "field": "withsecure.infection.name"
      }
    ],
    "relationships": [
      {
        "source": "host.hostname",
        "target": "file.path",
        "type": "infected by"
      }
    ]
  },
  {
    "value": "Executable file {{file.path}} blocked on {{host.hostname}}",
    "conditions": [
      {
        "field": "host.hostname"
      },
      {
        "field": "event.dataset",
        "value": "deepGuard"
      }
    ],
    "relationships": [
      {
        "source": "host.hostname",
        "target": "file.path",
        "type": "prevented execution"
      }
    ]
  },
  {
    "value": "Microsoft antimalware blocked execution of {{withsecure.amsi.content_name}} on {{host.hostname}}",
    "conditions": [
      {
        "field": "host.hostname"
      },
      {
        "field": "event.dataset",
        "value": "AMSI"
      }
    ],
    "relationships": [
      {
        "source": "host.hostname",
        "target": "withsecure.amsi.content_name",
        "type": "prevented execution"
      }
    ]
  },
  {
    "value": "Network connection by {{process.name}} blocked on {{host.hostname}} between {{source.address}}:{{source.port}} and {{destination.address}}:{{destination.port}}",
    "conditions": [
      {
        "field": "event.dataset",
        "value": "firewall"
      }
    ],
    "relationships": [
      {
        "source": "source.address",
        "target": "destination.address",
        "type": "attempted connection on"
      }
    ]
  },
  {
    "value": "Browsing protection blocked {{url.full}} requested by {{process.name}} on {{host.hostname}}",
    "conditions": [
      {
        "field": "event.dataset",
        "value": "reputationBasedBrowsing"
      }
    ],
    "relationships": [
      {
        "source": "process.name",
        "target": "url.full",
        "type": "requested"
      },
      {
        "target": "host.hostname",
        "source": "process.name",
        "type": "execute on"
      }
    ]
  }
]